mk_rpi_lcd/__init__.py
Mk_RPI_LCD-0.0.9.dist-info/LICENSE
Mk_RPI_LCD-0.0.9.dist-info/METADATA
Mk_RPI_LCD-0.0.9.dist-info/WHEEL
Mk_RPI_LCD-0.0.9.dist-info/top_level.txt
Mk_RPI_LCD-0.0.9.dist-info/RECORD
