Metadata-Version: 2.1
Name: Mk-RPI-LCD
Version: 0.0.9
Summary: Raspberry pi SDA/SSCL
Home-page: https://mknxgn.com/
Author: Mark Cartagena
Author-email: mark@mknxgn.com
License: UNKNOWN
Platform: UNKNOWN
Classifier: Programming Language :: Python :: 3
Classifier: License :: OSI Approved :: MIT License
Classifier: Operating System :: OS Independent
Requires-Dist: mknxgn-essentials
